amanibhavam/__init__.py
amanibhavam-0.1.21.dist-info/entry_points.txt
amanibhavam-0.1.21.dist-info/WHEEL
amanibhavam-0.1.21.dist-info/METADATA
amanibhavam-0.1.21.dist-info/RECORD
