Metadata-Version: 2.1
Name: amanibhavam
Version: 0.1.21
Summary: 
Author: Amanibhavam
Author-email: iam@defn.sh
Requires-Python: >=3.8,<4.0
Classifier: Programming Language :: Python :: 3
Classifier: Programming Language :: Python :: 3.10
Classifier: Programming Language :: Python :: 3.8
Classifier: Programming Language :: Python :: 3.9
Requires-Dist: cdktf (>=0.10.4,<0.11.0)
Requires-Dist: cdktf-cdktf-provider-aws (>=7.0.55,<8.0.0)
Requires-Dist: cdktf-cdktf-provider-digitalocean (>=0.0.40,<0.0.41)
Requires-Dist: cdktf-cdktf-provider-github (>=0.7.62,<0.8.0)
Requires-Dist: cdktf-cdktf-provider-null (>=0.6.55,<0.7.0)
Requires-Dist: cdktf-cdktf-provider-tfe (>=0.2.58,<0.3.0)
Requires-Dist: defn-cdktf-provider-boundary (>=0.4.0,<0.5.0)
Requires-Dist: defn-cdktf-provider-buildkite (>=0.4.0,<0.5.0)
Requires-Dist: defn-cdktf-provider-cloudflare (>=0.4.0,<0.5.0)
Requires-Dist: defn-cdktf-provider-vault (>=0.4.0,<0.5.0)
